validCSV/__init__.py
validCSV/verify.py
validCSV-0.0.1.dist-info/LICENSE.md
validCSV-0.0.1.dist-info/METADATA
validCSV-0.0.1.dist-info/WHEEL
validCSV-0.0.1.dist-info/top_level.txt
validCSV-0.0.1.dist-info/RECORD
