Metadata-Version: 2.1
Name: validCSV
Version: 0.0.1
Summary: A small and performance-oriented CSV header linter / verifier
Home-page: https://github.com/bmalbusca/validCSV
Author: Bruno Figueiredo
Author-email: bmalbusca@protonmail.com
License: MIT
Platform: UNKNOWN
Classifier: Development Status :: 1 - Planning
Classifier: Intended Audience :: Science/Research
Classifier: License :: OSI Approved :: MIT License
Classifier: Operating System :: POSIX :: Linux
Classifier: Programming Language :: Python :: 3
Classifier: Programming Language :: Python :: 3.5
Classifier: Programming Language :: Python :: 3.6
Classifier: Programming Language :: Python :: 3.7
Classifier: Programming Language :: Python :: 3.8
Classifier: Programming Language :: Python :: 3.8
